{
    "news": [
        {
            "id": 1,
            "title": "News Article 1",
            "description": "New This is the first news article",
            "category": "Sports"
        },
        {
            "id": 2,
            "title": "News Article 2",
            "description": "This is the second news article",
            "category": "politics"
        },
        {
            "id": 3,
            "title": "News Article 3",
            "description": "This is the third news article",
            "category": "Sports"
        },
        {
            "id": 4,
            "title": "News Article 4",
            "description": "This is the fourth news article",
            "category": "Sports"
        }
    ],
    "dashboard":{
        "posts":80,
        "likes":100,
        "followers":20,
        "following":30
    },
    "events":[
        {
            "id":1,
            "title":"Event 1",
            "description":"This is the first event",
            "date":"2020-01-01",
            "time":"10:00",
            "location":"Sydney"
        },
        {
            "id":2,
            "title":"Event 2",
            "description":"This is the second event",
            "date":"2020-01-01",
            "time":"10:00",
            "location":"India"
        },
        {
            "id":3,
            "title":"Event 3",
            "description":"This is the third event",
            "date":"2020-01-01",
            "time":"10:00",
            "location":"Sydney"
        },
        {
            "id":4,
            "title":"Event 4",
            "description":"This is the fourth event",
            "date":"2020-01-01",
            "time":"10:00",
            "location":"India"
        }
    ]
}